worktreeflow/__init__.py
worktreeflow/py.typed
worktreeflow/wtf.py
worktreeflow-0.2.0.dist-info/WHEEL
worktreeflow-0.2.0.dist-info/entry_points.txt
worktreeflow-0.2.0.dist-info/METADATA
worktreeflow-0.2.0.dist-info/RECORD
