Metadata-Version: 2.3
Name: worktreeflow
Version: 0.2.0
Summary: Git workflow manager for feature branches using worktrees, shows you cli equivalent commands
Keywords: git,worktree,workflow,cli,github
Author: Steve Morin
Author-email: Steve Morin <steve.morin@gmail.com>
License: MIT
Classifier: Development Status :: 4 - Beta
Classifier: Environment :: Console
Classifier: Intended Audience :: Developers
Classifier: License :: OSI Approved :: MIT License
Classifier: Operating System :: OS Independent
Classifier: Programming Language :: Python :: 3
Classifier: Programming Language :: Python :: 3.9
Classifier: Programming Language :: Python :: 3.10
Classifier: Programming Language :: Python :: 3.11
Classifier: Programming Language :: Python :: 3.12
Classifier: Topic :: Software Development :: Version Control :: Git
Classifier: Topic :: Utilities
Requires-Dist: gitpython>=3.1.40
Requires-Dist: click>=8.1.0
Requires-Dist: rich>=13.0
Requires-Dist: typing-extensions>=4.0
Requires-Python: >=3.9
Project-URL: Homepage, https://github.com/smorinlabs/worktreeflow
Project-URL: Issues, https://github.com/smorinlabs/worktreeflow/issues
Project-URL: Repository, https://github.com/smorinlabs/worktreeflow
